chromie/__init__.py
chromie/app.py
chromie/cmds/check.py
chromie/cmds/coll.py
chromie/cmds/cp.py
chromie/cmds/dl.py
chromie/cmds/exp.py
chromie/cmds/imp.py
chromie/cmds/ls.py
chromie/cmds/ping.py
chromie/cmds/uri.py
chromio/__init__.py
chromio/assets/schemas/exp-file.json
chromio/client/__init__.py
chromio/client/_client.py
chromio/errors.py
chromio/filter/__init__.py
chromio/filter/errors.py
chromio/filter/loc.py
chromio/filter/metadata/Filter.g4
chromio/filter/metadata/Lexer.g4
chromio/filter/metadata/__init__.py
chromio/filter/metadata/_antlr4/FilterParser.py
chromio/filter/metadata/_antlr4/Lexer.py
chromio/filter/metadata/_core.py
chromio/filter/metadata/_parser.py
chromio/ie/__init__.py
chromio/ie/_db.py
chromio/ie/_rpt.py
chromio/ie/ck.py
chromio/ie/consts.py
chromio/ie/cp/__init__.py
chromio/ie/cp/copier.py
chromio/ie/cp/rpt.py
chromio/ie/dl/__init__.py
chromio/ie/dl/_downloader.py
chromio/ie/dl/gh.py
chromio/ie/dl/http.py
chromio/ie/exp/__init__.py
chromio/ie/exp/exporter.py
chromio/ie/exp/jsonl.py
chromio/ie/exp/reader.py
chromio/ie/exp/rpt.py
chromio/ie/field.py
chromio/ie/imp/__init__.py
chromio/ie/imp/importer.py
chromio/ie/imp/rpt.py
chromio/ie/imp/writer.py
chromio/tools/__init__.py
chromio/tools/_cmd.py
chromio/tools/db.py
chromio/uri/__init__.py
chromio/uri/parser.py
chromio/uri/uri.py
chromie_tool-0.7.0.dist-info/METADATA
chromie_tool-0.7.0.dist-info/WHEEL
chromie_tool-0.7.0.dist-info/entry_points.txt
chromie_tool-0.7.0.dist-info/RECORD
