Metadata-Version: 2.4
Name: chromie-tool
Version: 0.7.0
Summary: Chroma import/export tool.
License-Expression: GPL-3.0-or-later
Keywords: chroma,chromadb,cli,export,import,tool,vector database
Author: Raúl G. González
Author-email: raul@chromio.dev
Requires-Python: >=3.12.0, <3.14.0
Classifier: Development Status :: 3 - Alpha
Classifier: Intended Audience :: Developers
Classifier: Environment :: Console
Classifier: Operating System :: OS Independent
Classifier: Programming Language :: Python :: 3.13
Classifier: Topic :: Database
Classifier: Topic :: Software Development :: Libraries
Classifier: Topic :: Software Development :: Libraries :: Application Frameworks
Classifier: Topic :: Software Development :: Libraries :: Python Modules
Classifier: Topic :: Utilities
Requires-Dist: aiofiles (>=24.1.0,<25.0.0)
Requires-Dist: antlr4-python3-runtime (>=4.13.2,<5.0.0)
Requires-Dist: chromadb (>=1.3.4,<2.0.0)
Requires-Dist: httpx (>=0.28.1,<0.29.0)
Requires-Dist: jsonschema (>=4.25.1,<5.0.0)
Requires-Dist: sentence-transformers (>=5.1.2,<6.0.0)
Project-URL: Homepage, https://github.com/chromiodev/chromie
Project-URL: Repository, https://github.com/chromiodev/chromie
